oktadboto/__init__.py
oktadboto/test_oktadboto.py
oktadboto-0.0.2.dist-info/LICENSE
oktadboto-0.0.2.dist-info/METADATA
oktadboto-0.0.2.dist-info/WHEEL
oktadboto-0.0.2.dist-info/top_level.txt
oktadboto-0.0.2.dist-info/RECORD
