Metadata-Version: 2.1
Name: oktadboto
Version: 0.0.2
Summary: Boto3 RefreshableCredentials wrapping oktad system call
Home-page: https://github.com/upserve/oktadboto
Author: Upserve
Author-email: datascience@upserve.com
License: MIT
Platform: UNKNOWN
Classifier: Programming Language :: Python :: 3
Classifier: License :: OSI Approved :: MIT License
Classifier: Operating System :: OS Independent
Requires-Python: ~=3.7
Requires-Dist: boto3
Provides-Extra: dev
Requires-Dist: flake8 ; extra == 'dev'
Requires-Dist: black ; extra == 'dev'
